mg_conveyor/conveyor.py
mg_conveyor/exceptions.py
mg_conveyor/plugin_interfaces.py
mg_conveyor/__init__.py
mg_conveyor-1.0.0.dist-info/DESCRIPTION.rst
mg_conveyor-1.0.0.dist-info/METADATA
mg_conveyor-1.0.0.dist-info/metadata.json
mg_conveyor-1.0.0.dist-info/RECORD
mg_conveyor-1.0.0.dist-info/top_level.txt
mg_conveyor-1.0.0.dist-info/WHEEL
