Metadata-Version: 2.0
Name: mg-conveyor
Version: 1.0.0
Summary: A tool for having a sequential execution of plugins
Home-page: https://sourceforge.net/projects/mobgenconveyor
Author: Ronaldo Webb
Author-email: mobil3.g3nius@gmail.com
License: UNKNOWN
Keywords: tool plugin utility development dev
Platform: UNKNOWN
Classifier: Development Status :: 4 - Beta
Classifier: Environment :: Console
Classifier: Intended Audience :: End Users/Desktop
Classifier: Intended Audience :: Developers
Classifier: Intended Audience :: System Administrators
Classifier: Programming Language :: Python
Classifier: Topic :: Communications :: Email
Classifier: Topic :: Software Development :: Bug Tracking
Requires-Dist: yapsy
